airflow_provider_openmetadata/__init__.py
airflow_provider_openmetadata/hooks/__init__.py
airflow_provider_openmetadata/hooks/openmetadata.py
airflow_provider_openmetadata/lineage/__init__.py
airflow_provider_openmetadata/lineage/backend.py
airflow_provider_openmetadata/lineage/callback.py
airflow_provider_openmetadata/lineage/operator.py
airflow_provider_openmetadata/lineage/runner.py
airflow_provider_openmetadata/lineage/status.py
airflow_provider_openmetadata/lineage/config/__init__.py
airflow_provider_openmetadata/lineage/config/commons.py
airflow_provider_openmetadata/lineage/config/loader.py
airflow_provider_openmetadata/lineage/config/providers.py
metadata/__init__.py
metadata/__main__.py
metadata/__version__.py
metadata/cmd.py
metadata/antlr/__init__.py
metadata/antlr/split_listener.py
metadata/automations/__init__.py
metadata/automations/runner.py
metadata/cli/__init__.py
metadata/cli/backup.py
metadata/cli/dataquality.py
metadata/cli/db_dump.py
metadata/cli/docker.py
metadata/cli/ingest.py
metadata/cli/insight.py
metadata/cli/openmetadata_dag_config_migration.py
metadata/cli/openmetadata_imports_migration.py
metadata/cli/profile.py
metadata/cli/restore.py
metadata/cli/utils.py
metadata/clients/__init__.py
metadata/clients/aws_client.py
metadata/clients/domo_client.py
metadata/config/__init__.py
metadata/config/common.py
metadata/data_insight/__init__.py
metadata/data_insight/api/__init__.py
metadata/data_insight/api/workflow.py
metadata/data_insight/helper/data_insight_es_index.py
metadata/data_insight/processor/__init__.py
metadata/data_insight/processor/data_processor.py
metadata/data_insight/processor/entity_report_data_processor.py
metadata/data_insight/processor/web_analytic_report_data_processor.py
metadata/data_insight/runner/kpi_runner.py
metadata/data_insight/runner/run_result_registry.py
metadata/data_insight/sink/__init__.py
metadata/data_insight/sink/metadata_rest.py
metadata/data_quality/__init__.py
metadata/data_quality/api/__init__.py
idg_metadata_client-1.0.2.0.dist-info/LICENSE
idg_metadata_client-1.0.2.0.dist-info/METADATA
idg_metadata_client-1.0.2.0.dist-info/WHEEL
idg_metadata_client-1.0.2.0.dist-info/entry_points.txt
idg_metadata_client-1.0.2.0.dist-info/top_level.txt
idg_metadata_client-1.0.2.0.dist-info/RECORD
